manufacturing_forecast/__init__.py
manufacturing_forecast/data/__init__.py
manufacturing_forecast/data/converters.py
manufacturing_forecast/data/processors.py
manufacturing_forecast/models/__init__.py
manufacturing_forecast/models/base.py
manufacturing_forecast/models/catboost_model.py
manufacturing_forecast/models/factory.py
manufacturing_forecast/models/lightgbm_model.py
manufacturing_forecast/models/pls_model.py
manufacturing_forecast/models/random_forest_model.py
manufacturing_forecast/models/xgboost_model.py
manufacturing_forecast-0.2.0.dist-info/licenses/LICENSE
manufacturing_forecast-0.2.0.dist-info/METADATA
manufacturing_forecast-0.2.0.dist-info/WHEEL
manufacturing_forecast-0.2.0.dist-info/top_level.txt
manufacturing_forecast-0.2.0.dist-info/RECORD
